mkdocs_manuals_theme/__init__.py
mkdocs_manuals_theme/base.html
mkdocs_manuals_theme/main.html
mkdocs_manuals_theme/mkdocs_theme.yml
mkdocs_manuals_theme/search.html
mkdocs_manuals_theme/css/normalize.css
mkdocs_manuals_theme/css/theme.css
mkdocs_manuals_theme/fontello/demo.html
mkdocs_manuals_theme/fontello/css/animation.css
mkdocs_manuals_theme/fontello/css/fontello-codes.css
mkdocs_manuals_theme/fontello/css/fontello-embedded.css
mkdocs_manuals_theme/fontello/css/fontello-ie7-codes.css
mkdocs_manuals_theme/fontello/css/fontello-ie7.css
mkdocs_manuals_theme/fontello/css/fontello.css
mkdocs_manuals_theme/fontello/font/fontello.eot
mkdocs_manuals_theme/fontello/font/fontello.svg
mkdocs_manuals_theme/fontello/font/fontello.ttf
mkdocs_manuals_theme/fontello/font/fontello.woff
mkdocs_manuals_theme/fontello/font/fontello.woff2
mkdocs_manuals_theme/img/favicon.png
mkdocs_manuals_theme/js/theme.js
mkdocs_manuals_theme/parts/breadcrumb.html
mkdocs_manuals_theme/parts/nav.html
mkdocs_manuals_theme/parts/nav_link.html
mkdocs_manuals_theme-0.10.0.dist-info/LICENSE
mkdocs_manuals_theme-0.10.0.dist-info/METADATA
mkdocs_manuals_theme-0.10.0.dist-info/WHEEL
mkdocs_manuals_theme-0.10.0.dist-info/entry_points.txt
mkdocs_manuals_theme-0.10.0.dist-info/top_level.txt
mkdocs_manuals_theme-0.10.0.dist-info/RECORD
