Metadata-Version: 2.1
Name: mkdocs-manuals-theme
Version: 0.10.0
Summary: A theme for rendering manuals using mkdocs
Author-email: Mittal Analytics Pvt Ltd <pratyush@hey.com>
Project-URL: Homepage, https://github.com/Mittal-Analytics/mkdocs-manuals-theme
Requires-Python: >=3.7
License-File: LICENSE
Requires-Dist: mkdocs
Provides-Extra: dev
Requires-Dist: bumpver ; extra == 'dev'
Requires-Dist: build ; extra == 'dev'
Requires-Dist: twine ; extra == 'dev'
